checkdigit/__init__.py
checkdigit/damm.py
checkdigit/luhn.py
checkdigit/verhoeff.py
checkdigit_algorithms-1.0.0.dist-info/licenses/LICENSE
checkdigit_algorithms-1.0.0.dist-info/METADATA
checkdigit_algorithms-1.0.0.dist-info/WHEEL
checkdigit_algorithms-1.0.0.dist-info/top_level.txt
checkdigit_algorithms-1.0.0.dist-info/RECORD
